fastsweep-0.2.0.dist-info/RECORD
fastsweep-0.2.0.dist-info/WHEEL
fastsweep-0.2.0.dist-info/METADATA
fastsweep-0.2.0.dist-info/licenses/LICENSE
fastsweep/__init__.py
fastsweep/fastsweep_ext.cpython-38-darwin.so
