Metadata-Version: 2.1
Name: fastsweep
Version: 0.2.0
Summary: Eikonal solver using parallel fast sweeping.
Author-Email: Delio Vicini <delio.vicini@gmail.com>
Classifier: License :: OSI Approved :: BSD License
Project-URL: Homepage, https://github.com/rgl-epfl/fastsweep
Requires-Python: >=3.8
Requires-Dist: typing_extensions>=4.12; python_version < "3.11"
Requires-Dist: drjit==1.0.1
